qe/__init__.py
qe/qe.py
test/__init__.py
test/test_qe.py
qe-2.0.0.dist-info/METADATA
qe-2.0.0.dist-info/WHEEL
qe-2.0.0.dist-info/top_level.txt
qe-2.0.0.dist-info/RECORD
