Metadata-Version: 2.1
Name: qe
Version: 2.0.0
Summary: turn pandas dataframe into an excel instance on Windows
Home-page: https://github.com/aeorxc/qe
Author: aeorxc
Author-email: author@example.com
License: UNKNOWN
Project-URL: Source, https://github.com/aeorxc/qe
Platform: UNKNOWN
Classifier: Programming Language :: Python :: 3
Classifier: License :: OSI Approved :: MIT License
Classifier: Operating System :: OS Independent
Requires-Python: >=3.6
Requires-Dist: pandas
Requires-Dist: xlsxwriter
